hydnam/__init__.py
hydnam/dataset.py
hydnam/hydnam.py
hydnam/model_output.py
hydnam/parameters.py
hydnam/statistical_metrics.py
hydnam-2.0.0.dist-info/LICENSE
hydnam-2.0.0.dist-info/METADATA
hydnam-2.0.0.dist-info/WHEEL
hydnam-2.0.0.dist-info/RECORD
