Metadata-Version: 2.1
Name: hydnam
Version: 2.0.0
Summary: Python implementation of NedborAfstromnings Model (NAM) lumped rainfall–runoff model
Home-page: https://github.com/duynguyen02/hydnam
License: MIT
Author: Duy Nguyen
Author-email: duynguyen02.dev@gmail.com
Requires-Python: >=3.10,<4.0
Classifier: License :: OSI Approved :: MIT License
Classifier: Programming Language :: Python :: 3
Classifier: Programming Language :: Python :: 3.10
Classifier: Programming Language :: Python :: 3.11
Classifier: Programming Language :: Python :: 3.12
Classifier: Programming Language :: Python :: 3.13
Requires-Dist: hydutils (>=2.0.0,<3.0.0)
Requires-Dist: matplotlib (>=3.9.2,<4.0.0)
Requires-Dist: numpy (>=2.1.3,<3.0.0)
Requires-Dist: pandas (>=2.2.3,<3.0.0)
Requires-Dist: scipy (>=1.14.1,<2.0.0)
Project-URL: Repository, https://github.com/duynguyen02/hydnam
